polars_readstat-0.11.1.dist-info/METADATA
polars_readstat-0.11.1.dist-info/WHEEL
polars_readstat-0.11.1.dist-info/licenses/LICENSE
polars_readstat/__init__.py
polars_readstat/py.typed
polars_readstat/polars_readstat_rs.abi3.so
polars_readstat-0.11.1.dist-info/RECORD
