Metadata-Version: 2.4
Name: polars-readstat
Version: 0.11.1
Classifier: Programming Language :: Rust
Classifier: Programming Language :: Python :: Implementation :: CPython
Classifier: Programming Language :: Python :: Implementation :: PyPy
Requires-Dist: polars>=1.25.2
License-File: LICENSE
Summary: Read SAS (sas7bdat), Stata (dta), and SPSS (sav) files with polars
Author: Jonathan Rothbaum <jon.rothbaum@gmail.com
Author-email: Jon Rothbaum <jlrothbaum@gmail.com>
License: MIT
Requires-Python: >=3.9
Project-URL: Homepage, https://github.com/jrothbaum/polars_readstat
Project-URL: Repository, https://github.com/jrothbaum/polars_readstat
Project-URL: Bug-Tracker, https://github.com/jrothbaum/polars_readstat/issues
